saurongaze/__init__.py
saurongaze/__main__.py
saurongaze/demo.py
saurongaze/gaze_estimator.py
saurongaze/main.py
saurongaze/transforms.py
saurongaze/types.py
saurongaze/utils.py
saurongaze/common/__init__.py
saurongaze/common/camera.py
saurongaze/common/eye.py
saurongaze/common/face.py
saurongaze/common/face_model.py
saurongaze/common/face_parts.py
saurongaze/common/visualizer.py
saurongaze/config/__init__.py
saurongaze/config/defaults.py
saurongaze/data/calib/normalized_camera_params_eye.yaml
saurongaze/data/calib/normalized_camera_params_face.yaml
saurongaze/data/calib/sample_params.yaml
saurongaze/head_pose_estimation/__init__.py
saurongaze/head_pose_estimation/face_landmark_estimator.py
saurongaze/head_pose_estimation/head_pose_normalizer.py
saurongaze/models/__init__.py
saurongaze/models/mpiifacegaze/__init__.py
saurongaze/models/mpiifacegaze/resnet_simple.py
saurongaze/models/mpiifacegaze/backbones/__init__.py
saurongaze/models/mpiifacegaze/backbones/resnet_simple.py
saurongaze/models/mpiigaze/__init__.py
saurongaze/models/mpiigaze/resnet_preact.py
saurongaze-0.0.1.dist-info/LICENSE
saurongaze-0.0.1.dist-info/WHEEL
saurongaze-0.0.1.dist-info/METADATA
saurongaze-0.0.1.dist-info/RECORD
