Metadata-Version: 2.1
Name: saurongaze
Version: 0.0.1
Summary: saurongaze - accurate gaze and head pose information
Home-page: https://github.com/ollipal/saurongaze
License: UNKNOWN
Author: Olli Paloviita
Author-email: olli.paloviita@gmail.com
Classifier: License :: OSI Approved :: MIT License
